chunkey_bert/__init__.py
chunkey_bert/model.py
chunkey_bert-0.2.0.dist-info/LICENSE
chunkey_bert-0.2.0.dist-info/METADATA
chunkey_bert-0.2.0.dist-info/WHEEL
chunkey_bert-0.2.0.dist-info/RECORD
