Metadata-Version: 2.1
Name: chunkey-bert
Version: 0.2.0
Summary: Modification of the KeyBERT method to extract keywords and keyphrases using chunks. This provides better results, especialy when handling long documents.
Home-page: https://github.com/yaniv-shulman/chunkey-keybert
Keywords: machine learning
Author: Yaniv Shulman
Author-email: yaniv@shulman.info
Requires-Python: >=3.9,<3.12
Classifier: Intended Audience :: Developers
Classifier: Intended Audience :: Science/Research
Classifier: License :: OSI Approved :: MIT License
Classifier: Programming Language :: Python :: 3
Classifier: Programming Language :: Python :: 3.9
Classifier: Programming Language :: Python :: 3.10
Classifier: Programming Language :: Python :: 3.11
Classifier: Topic :: Scientific/Engineering
Classifier: Topic :: Scientific/Engineering :: Artificial Intelligence
Requires-Dist: keybert (>=0.8.4,<0.9.0)
Project-URL: Repository, https://github.com/yaniv-shulman/chunkey-bert
